t_ai/__init__.py
t_ai/t_agent.py
t_ai/PrebuiltTools/__init__.py
t_ai/PrebuiltTools/google_tools.py
t_ai/utils/__init__.py
t_ai/utils/helper_functions.py
t_ai_project-0.1.9.dist-info/METADATA
t_ai_project-0.1.9.dist-info/WHEEL
t_ai_project-0.1.9.dist-info/RECORD
